UART_TX/MUX.v
/******************************************************************************
* Module: Private - MUX Block 
*
* File Name: MUX.v
*
* Description: implement a parameterized 4X1 MUX.
*
* Author: Mohamed A. Eladawy
*
*******************************************************************************/
//********************Port Declaration*************************//

module MUX  #(

parameter Selction_Width = 2  ,                                //initialize a parameter variable with value 32 
parameter Data_Size_C    = 32 )                                //initialize a parameter variable with value 32 

(
  
input wire [Selction_Width-1 :0]           SEL          , //Declaring the Variable As an Input Port with Width 2 bit
input wire                                 Ser_Data_Mux , //Declaring the Variable As an Input Port with Width 1 bits
input wire                                 Parity_Bit   , //Declaring the Variable As an Input Port with Width 1 bits
output reg                                 TX_OUT         //Declaring the Variable As an Output Port with Width 1 bits    

);

//******************** Parameters Initialization  ******************//

localparam          ONE      = 1'b1   , //initialize a parameter variable with a binary value 1
                    ZERO     = 1'b0   , //initialize a parameter variable with a binary value 0
                    Start    = 2'b00  , //initialize a parameter variable with a binary value 2'b00
                    stop     = 2'b01  , //initialize a parameter variable with a binary value 2'b01
                    ser_data = 2'b10  , //initialize a parameter variable with a binary value 2'b10
                    Parity   = 2'b11  ; //initialize a parameter variable with a binary value 2'b10
                                       
//*************************** The RTL Code *****************************//
//**************** Starting Combinational Always Block *****************//

always @ (*)

begin 

    case (SEL) 
    
    Start  :  begin
              
              TX_OUT = ZERO ; 
              
              end 
                  
    stop  :  begin
              
              TX_OUT = ONE ; 
              
              end 
                                
    ser_data  :  begin
              
              TX_OUT = Ser_Data_Mux ; 
              
              end 
              
    Parity  :  begin
              
              TX_OUT = Parity_Bit ; 
              
              end                  
       
      
    endcase
 
end 

//**********************************************************************//

endmodule

UART_TX/Parity_Calculator.v
/******************************************************************************
*
* Module: Private - Parity_Block
*
* File Name: Parity_Block.v
*
* Description:  This Block Is Used To Calculate The Fkn Even And Fkn Odd 
*               Parity
*               
* Author: Mohamed A. Eladawy
*
*******************************************************************************/
//************************** Port Declaration ********************************//

module Parity_Block # (

parameter INPUT_WIDTH   = 8 ) //initialize a parameter variable with value 8

(

input wire [INPUT_WIDTH-1 : 0 ]  P_Data       ,  //Declaring the Variable As an Input Port with width 8 bits 
input wire                       Data_Valid   ,  //Declaring the Variable As an Input Port with width 1 bit
input wire                       CLK          ,  //Declaring the Variable As an Input Port with width 1 bit
input wire                       RST          ,  //Declaring the Variable As an Input Port with width 1 bit
input wire                       Par_Type     ,  //Declaring the Variable As an Input Port with width 1 bit
output reg                       Par_bit         //Declaring the Variable As an Input Port with width 1 bit

);

//******************** Parameters Initialization  ******************//

localparam          ONE                    = 1'b1   ,//initialize a parameter variable with a binary value 1
                    ZERO                   = 1'b0   ,//initialize a parameter variable with a binary value 0
                    Serial_Register_width  = 8      ;//initialize a parameter variable with a binary value 8

//********************Internal Signal Declaration*****************//

reg [ Serial_Register_width-1 :0]  Register_Parity ;               //Declaring The Variable To Use it As a register Inside The Always Block

//************************* The RTL Code ***************************//
/*************** Starting The Sequential Always Block ***************/

always @ (posedge CLK or negedge RST)
 begin
  if(!RST)
    
       begin
 
          Register_Parity <= ZERO ;
          
       end
 
  else if ( Data_Valid ) 
   
       begin
   
          Register_Parity <= P_Data ;

       end
       
  else 
    
       if ( Par_Type )  
            
        begin
         
		 Par_bit <= ~^Register_Parity ;
      
 
       end  
       
       
     else 
       
       begin
   
            Par_bit <= ^Register_Parity ;
 
       end
       

 end





/*********************************************************************/

endmodule

UART_TX/FSM.v
/******************************************************************************
*
* Module: Private - FSM Block 
*
* File Name: FSM.v
*
* Description:  This File Is Used To Make The Mux Enable For To Make The 
*               Fram And Output Busy Signal 
*               
* Author: Mohamed A. Eladawy
*
*******************************************************************************/
//************************** Port Declaration ********************************//

module FSM (

input      wire        CLK            , //Declaring the Variable As an Input Port with width 1 bit 
input      wire        RST            , //Declaring the Variable As an Input Port with width 1 bit 
input      wire        Data_Valid_Fsm , //Declaring the Variable As an Input Port with width 1 bit  
input      wire        Par_Enable     , //Declaring the Variable As an Input Port with width 1 bit
input      wire        SER_DONE       , //Declaring the Variable As an Input Port with width 1 bit
output     reg         SER_ENABLE     , //Declaring the Variable As an Input Port with width 1 bit    
output     reg         Busy           , //Declaring the Variable As an Output Port with width 1 bit 
output     reg  [1 :0] Mux_Sel          //Declaring the Variable As an Output Port with width 1 bit 

);

//******************** Parameters Initialization  ******************//

localparam          IDLE      = 3'b000  , //initialize a parameter variable As A first State   ( IDLE STATE )
                    Starting  = 3'b001  , //initialize a parameter variable As A Seconed State ( Starting STATE )
                    Transfer  = 3'b010  , //initialize a parameter variable As A Third State   ( Parity STATE )
                    parity    = 3'b011  , //initialize a parameter variable As A Third State   ( Parity STATE )
                    Ending    = 3'b100  , //initialize a parameter variable As A Fourth State  ( Ending STATE ) 
                    ONE       = 1'b1    , //initialize a parameter variable with a binary value 1
                    ZERO      = 1'b0    ; //initialize a parameter variable with a binary value 0
                    
//******************** Internal Signal Declaration *****************//

reg      [2:0]      current_state ,
                    next_state    ;
                    

//************************* The RTL Code ***************************//

/*************** Starting The Sequential Always Block ***************/

always @ (posedge CLK or negedge RST)
 begin
  if(!RST)
    
       begin
 
          current_state <= IDLE ;
          
       end
  else
   
       begin
   
          current_state <= next_state ;
 
       end

 end

/*************** Starting The Combinational Always Block ***************/

always @ (*)
 
 
 begin
    Busy       = ZERO    ;
    Mux_Sel    = 2'b01   ;
    next_state = IDLE    ;
    SER_ENABLE = ZERO    ;
   case (current_state)
 
   IDLE   :  begin
             
              Busy    = ZERO ;
              
              if( Data_Valid_Fsm )
             
                begin
               
                   next_state = Starting  ;
               
                end
             
              else   
              
                begin
              
                   next_state = IDLE ;
              
                end  
             end
             
   Starting  :  begin
              
              Busy       = ONE       ;
              Mux_Sel    = 2'b00     ;
              
              next_state = Transfer  ;

                end
  
   Transfer  :  begin
              
              
              Busy       = ONE       ;
              Mux_Sel    = 2'b10     ;
              SER_ENABLE = ONE       ;
              SER_ENABLE = ONE       ;
              
     if ( SER_DONE ) 
             
         begin 
                
              if(Par_Enable)
               
                begin
               
                 next_state = parity  ;
               
                end
             
              else  
             
                begin
             
                 next_state = Ending  ;
             
                end 
                
          end 
          
        else 
              
              begin 
              
              next_state = Transfer  ;
              
              end        
             
             end

parity  :  begin
              
              Busy       = ONE     ;
              Mux_Sel    = 2'b11   ;
              next_state = Ending  ;
              
           end 

Ending  :  begin
              
              Busy       = ONE     ;
              Mux_Sel    = 2'b01   ;
              next_state = IDLE    ;
              SER_ENABLE = ZERO    ;

           end
default : 
             begin
             
                 next_state = IDLE  ;
                 Busy       = ZERO  ;
             
             end  
   endcase   
 end



/*********************************************************************/

endmodule

UART_TX/Serializer.v
/******************************************************************************
*
* Module: Private - Serializer Block 
*
* File Name: Serializer.v
*
* Description:  This Block Is Used To Transform The Input Data From Parrlrl 
*               To Serial Data 
*
* Author: Mohamed A. Eladawy
*
*******************************************************************************/

//********************Port Declaration*************************//
module  Serializer # (

parameter INPUT_WIDTH   = 8 ) //initialize a parameter variable with value 8 
  
(

input wire [INPUT_WIDTH-1 : 0 ]  P_Data       ,  //Declaring the Variable As an Input Port with width 8 bits 
input wire                       Data_Valid   ,  //Declaring the Variable As an Input Port with width 1 bit
input wire                       CLK          ,  //Declaring the Variable As an Input Port with width 1 bit
input wire                       RST          ,  //Declaring the Variable As an Input Port with width 1 bit
input wire                       Busy_Sir     ,  //Declaring the Variable As an Input Port with width 1 bit
input wire                       Ser_Enable   ,  //Declaring the Variable As an Input Port with width 1 bit
output wire                       Ser_Data     ,  //Declaring the Variable As an Input Port with width 1 bit
output wire                      Ser_Done        //Declaring the Variable As an output Port with width 1 bit    

); 
//****************** Parameeters Initialization  ****************//

localparam          ONE                    = 1'b1   ,//initialize a parameter variable with a binary value 1
                    ZERO                   = 1'b0   ,//initialize a parameter variable with a binary value 0
                    Serial_Register_width  = 8      ;//initialize a parameter variable with a binary value 8

//********************Internal Signal Declaration*****************//

reg [ Serial_Register_width-1 :0]  Serial_Register ;               //Declaring The Variable To Use it As a register Inside The Always Block
reg [2 : 0 ]                       Counter         ;
                    
//*************************** The RTL Code *****************************//
/*************** Starting The Combinational Always Block ***************/

always@( posedge CLK or negedge RST )

 begin
      
      if(!RST)
        
           begin
              
               Serial_Register <= 'b0 ;
                   
               
           end
           
       else if(Data_Valid &! Busy_Sir )
       
           begin 
            
              Serial_Register <= P_Data ;
              
           end
            
      else    if ( Ser_Enable ) 
           begin
             
   
              //Ser_Data        <= Serial_Register[7]      ;
              Serial_Register <= (Serial_Register<<1)    ;
              
           end
 
      end


always @(posedge CLK or negedge RST )

begin 
        if(!RST)
        
           begin
              
               Counter <= 'b0 ;
                   
               
           end
  
      else if ( Ser_Enable   ) 
        
        begin 
          
          Counter = Counter + 1 ; 
          
        end 
        
       else  
         
         Counter <= 'b0 ;
      
  
end 

assign Ser_Done = ( Counter == 3'b111 ) ; 
assign Ser_Data = Serial_Register[7] ; 
endmodule

UART_TX/UART_TX.v
/******************************************************************************
*
* Module: Private - UART Transmiter Block
*
* File Name: UART_TX.v
*
* Description:  this file is used for implementation of the UART Transmiter
*
* Author: Mohamed A. Eladawy
*
*******************************************************************************/
module UART_TX # (
  
parameter Data_Width = 8  )  //initialize a parameter variable with value 8

(

input wire    [Data_Width-1 :0]        P_DATA_UART         , //Declaring the Variable As an Input Port with width 8 bit
input wire                             DATA_VALID_UART     , //Declaring the Variable As an Input Port with width 1 bit 
input wire                             PAR_EN_UART         , //Declaring the Variable As an Input Port with width 1 bit
input wire                             PAR_TYPE_UART       , //Declaring the Variable As an Input Port with width 1 bit
input wire                             RST_UART            , //Declaring the Variable As an Input Port with width 1 bit
input wire                             CLK_UART            , //Declaring the Variable As an Input Port with width 1 bit
output wire                            TX_OUT_UART         , //Declaring the Variable As an Input Port with width 1 bit 
output wire                            BUSY_UART             //Declaring the Variable As an Input Port with width 1 bit 

);

//****************** Parameeters Initialization  ****************//

localparam         Out_Width           = 32 ;            //initialize a parameter variable with a binary value 32

//********************Internal Signal Declaration*****************//

wire                       SER_DONE_UART    ; //Declaring the Variable As a wire 
wire                       SER_EN_UART      ; //Declaring the Variable As a wire
wire                       SER_DATA_UART    ; //Declaring the Variable As a wire 
wire                       PAR_BIT_UART     ; //Declaring the Variable As a wire
wire   [1 :0]              MUX_SEL_UART     ; //Declaring the Variable As a wire
       
                              
//********************************************************************//

//******************** Port Mapping For Every Block ******************//


//******************** Serializer Block Port  Mapping   ******************//

Serializer SERIALIZER_B ( //Instantiation of the control unit.

.P_Data(P_DATA_UART)         ,
.Data_Valid(DATA_VALID_UART) ,
.CLK(CLK_UART)               ,
.RST(RST_UART)               ,
.Ser_Enable(SER_EN_UART)     ,
.Busy_Sir(BUSY_UART)         ,
.Ser_Data(SER_DATA_UART)     ,
.Ser_Done (SER_DONE_UART)     

);

//******************** FSM Block Port  Mapping   ******************//

FSM FSM_B( //Instantiation of the data path block.

.CLK ( CLK_UART )                 ,
.RST (RST_UART)                   ,
.Data_Valid_Fsm(DATA_VALID_UART)  ,
.Par_Enable(PAR_EN_UART)          ,
.SER_DONE(SER_DONE_UART)          ,
.SER_ENABLE(SER_EN_UART)          ,
.Busy (BUSY_UART)                 ,
.Mux_Sel (MUX_SEL_UART)   

);

//******************** PARITY BLOCK Block Port  Mapping   ******************//

Parity_Block PARITY_BLOCK_U ( //Instantiation of the DATA_MEMORY block.

.P_Data(P_DATA_UART)         ,
.Data_Valid(DATA_VALID_UART) ,
.CLK(CLK_UART)               ,
.RST(RST_UART )              ,
.Par_Type(PAR_TYPE_UART)     ,
.Par_bit(PAR_BIT_UART)      

);

//******************** MUX Block Port  Mapping   ******************//


 MUX  MUX_U ( //Instantiation of the Instruction_Memory block.

.SEL(MUX_SEL_UART)             ,
.Ser_Data_Mux(SER_DATA_UART)   ,
.Parity_Bit(PAR_BIT_UART)      ,
.TX_OUT(TX_OUT_UART)   

);


endmodule

UART_TX/UART_TX_tb.v
/******************************************************************************
*
* Module: Private - UART Transmiter Block
*
* File Name: UART_TX_tb.v
*
* Description:  this file is used for testing implementation of the UART Transmiter
*
* Author: Mohamed A. Eladawy
*
*******************************************************************************/
module  UART_TX_tb  () ;
  

// all design inputs are defined in testbench as reg to be used inside initial block 
// all design outputs are defined in testbench as wire   
  reg              RST_tb             ;
  reg              CLK_tb             ;
  reg   [7:0]      P_DATA_UART_tb     ;
  reg              DATA_VALID_UART_tb ;  
  reg              PAR_EN_UART_tb     ;
  reg              PAR_TYPE_UART_tb   ;
  wire             TX_OUT_UART        ;  
  wire             BUSY_UART          ;  

/***********************************************************************/ 
initial 
  begin
    $dumpfile(" UART_TX.vcd") ;
    $dumpvars ;
    //initial values
    RST_tb     = 1'b0     ;
    CLK_tb     = 1'b0     ;
    P_DATA_UART_tb = 8'b0 ;
    DATA_VALID_UART_tb = 1'b0 ; 
    PAR_EN_UART_tb = 1'b0     ;
   
/***********************************************************************/    
   
    $display ("TEST CASE 1") ;  // 
    #2
    RST_tb     = 1'b0  ;
    DATA_VALID_UART_tb = 1'b0 ; 
    #2
    RST_tb             = 1'b1         ;
    P_DATA_UART_tb     = 8'b1110_0110 ;
    DATA_VALID_UART_tb = 1'b1         ;
    PAR_EN_UART_tb     = 1'b1         ;
    PAR_TYPE_UART_tb   = 1'b1         ;
    #10
     DATA_VALID_UART_tb = 1'b0         ;
    #40
    DATA_VALID_UART_tb = 1'b1         ;
    #10 
    DATA_VALID_UART_tb = 1'b0         ;
    #60
    P_DATA_UART_tb     = 8'b1101_0010 ;
    DATA_VALID_UART_tb = 1'b1         ;
    PAR_EN_UART_tb     = 1'b1         ;
    PAR_TYPE_UART_tb   = 1'b1         ;
    #10
     DATA_VALID_UART_tb = 1'b0         ;
    #200

/***********************************************************************/    
       

    #100
    $finish ;  
  
      
end 

// Clock Generator  
  always #5 CLK_tb = !CLK_tb ;
  
// instaniate design instance 
 UART_TX DUT (

.CLK_UART(CLK_tb)                      ,
.RST_UART(RST_tb)                      ,
.P_DATA_UART(P_DATA_UART_tb)           ,
.DATA_VALID_UART(DATA_VALID_UART_tb)   ,
.PAR_EN_UART(PAR_EN_UART_tb)           ,
.PAR_TYPE_UART(PAR_TYPE_UART_tb)       ,
.BUSY_UART(BUSY_UART)                  ,
.TX_OUT_UART(TX_OUT_UART)

);

  
endmodule

UART_TX/ UART_TX.vcd
$date
	Sat Oct 01 14:39:14 2022
$end
$version
	ModelSim Version 10.1d
$end
$timescale
	1ps
$end
$scope module UART_TX_tb $end
$var reg 1 ! RST_tb $end
$var reg 1 " CLK_tb $end
$var reg 8 # P_DATA_UART_tb [7:0] $end
$var reg 1 $ DATA_VALID_UART_tb $end
$var reg 1 % PAR_EN_UART_tb $end
$var reg 1 & PAR_TYPE_UART_tb $end
$var wire 1 ' TX_OUT_UART $end
$var wire 1 ( BUSY_UART $end
$scope module DUT $end
$var parameter 32 ) Data_Width $end
$var parameter 32 * Out_Width $end
$var wire 1 + P_DATA_UART [7] $end
$var wire 1 , P_DATA_UART [6] $end
$var wire 1 - P_DATA_UART [5] $end
$var wire 1 . P_DATA_UART [4] $end
$var wire 1 / P_DATA_UART [3] $end
$var wire 1 0 P_DATA_UART [2] $end
$var wire 1 1 P_DATA_UART [1] $end
$var wire 1 2 P_DATA_UART [0] $end
$var wire 1 3 DATA_VALID_UART $end
$var wire 1 4 PAR_EN_UART $end
$var wire 1 5 PAR_TYPE_UART $end
$var wire 1 6 RST_UART $end
$var wire 1 7 CLK_UART $end
$var wire 1 ' TX_OUT_UART $end
$var wire 1 ( BUSY_UART $end
$var wire 1 8 SER_DONE_UART $end
$var wire 1 9 SER_EN_UART $end
$var wire 1 : SER_DATA_UART $end
$var wire 1 ; PAR_BIT_UART $end
$var wire 1 < MUX_SEL_UART [1] $end
$var wire 1 = MUX_SEL_UART [0] $end
$scope module SERIALIZER_B $end
$var parameter 32 > INPUT_WIDTH $end
$var parameter 1 ? ONE $end
$var parameter 1 @ ZERO $end
$var parameter 32 A Serial_Register_width $end
$var wire 1 + P_Data [7] $end
$var wire 1 , P_Data [6] $end
$var wire 1 - P_Data [5] $end
$var wire 1 . P_Data [4] $end
$var wire 1 / P_Data [3] $end
$var wire 1 0 P_Data [2] $end
$var wire 1 1 P_Data [1] $end
$var wire 1 2 P_Data [0] $end
$var wire 1 3 Data_Valid $end
$var wire 1 7 CLK $end
$var wire 1 6 RST $end
$var wire 1 ( Busy_Sir $end
$var wire 1 9 Ser_Enable $end
$var wire 1 : Ser_Data $end
$var wire 1 8 Ser_Done $end
$var reg 8 B Serial_Register [7:0] $end
$var reg 3 C Counter [2:0] $end
$upscope $end
$scope module FSM_B $end
$var parameter 3 D IDLE $end
$var parameter 3 E Starting $end
$var parameter 3 F Transfer $end
$var parameter 3 G parity $end
$var parameter 3 H Ending $end
$var parameter 1 I ONE $end
$var parameter 1 J ZERO $end
$var wire 1 7 CLK $end
$var wire 1 6 RST $end
$var wire 1 3 Data_Valid_Fsm $end
$var wire 1 4 Par_Enable $end
$var wire 1 8 SER_DONE $end
$var reg 1 K SER_ENABLE $end
$var reg 1 L Busy $end
$var reg 2 M Mux_Sel [1:0] $end
$var reg 3 N current_state [2:0] $end
$var reg 3 O next_state [2:0] $end
$upscope $end
$scope module PARITY_BLOCK_U $end
$var parameter 32 P INPUT_WIDTH $end
$var parameter 1 Q ONE $end
$var parameter 1 R ZERO $end
$var parameter 32 S Serial_Register_width $end
$var wire 1 + P_Data [7] $end
$var wire 1 , P_Data [6] $end
$var wire 1 - P_Data [5] $end
$var wire 1 . P_Data [4] $end
$var wire 1 / P_Data [3] $end
$var wire 1 0 P_Data [2] $end
$var wire 1 1 P_Data [1] $end
$var wire 1 2 P_Data [0] $end
$var wire 1 3 Data_Valid $end
$var wire 1 7 CLK $end
$var wire 1 6 RST $end
$var wire 1 5 Par_Type $end
$var reg 1 T Par_bit $end
$var reg 8 U Register_Parity [7:0] $end
$upscope $end
$scope module MUX_U $end
$var parameter 32 V Selction_Width $end
$var parameter 32 W Data_Size_C $end
$var parameter 1 X ONE $end
$var parameter 1 Y ZERO $end
$var parameter 2 Z Start $end
$var parameter 2 [ stop $end
$var parameter 2 \ ser_data $end
$var parameter 2 ] Parity $end
$var wire 1 < SEL [1] $end
$var wire 1 = SEL [0] $end
$var wire 1 : Ser_Data_Mux $end
$var wire 1 ; Parity_Bit $end
$var reg 1 ^ TX_OUT $end
$upscope $end
$upscope $end
$upscope $end
$enddefinitions $end
#0
$dumpvars
0!
0"
b0 #
0$
0%
x&
b0 B
b0 C
0K
0L
b1 M
b0 N
b0 O
xT
b0 U
1^
b1000 )
b100000 *
b1000 >
b1 ?
b0 @
b1000 A
b0 D
b1 E
b10 F
b11 G
b100 H
b1 I
b0 J
b1000 P
b1 Q
b0 R
b1000 S
b10 V
b100000 W
b1 X
b0 Y
b0 Z
b1 [
b10 \
b11 ]
1'
0(
08
09
0:
x;
1=
0<
x5
04
03
02
01
00
0/
0.
0-
0,
0+
06
07
$end
#4
1!
b11100110 #
1$
1%
1&
11
10
1-
1,
1+
15
16
13
14
b1 O
#5
1"
17
b11100110 B
b1 N
b11100110 U
1:
b0 O
1L
b0 M
b10 O
1(
0=
0^
0'
#10
0"
07
#14
0$
03
0L
b1 M
b0 O
1L
b0 M
b10 O
#15
1"
17
b10 N
1T
1;
0L
b1 M
b0 O
1L
b10 M
1K
b10 O
19
1<
1^
1'
#20
0"
07
#25
1"
17
b1 C
b11001100 B
#30
0"
07
#35
1"
17
b10 C
b10011000 B
#40
0"
07
#45
1"
17
b11 C
b110000 B
0:
0^
0'
#50
0"
07
#54
1$
13
0L
b1 M
b0 O
0K
1L
b10 M
1K
b10 O
#55
1"
17
b100 C
b1100000 B
#60
0"
07
#64
0$
03
0L
b1 M
b0 O
0K
1L
b10 M
1K
b10 O
#65
1"
17
b101 C
b11000000 B
1:
1^
1'
#70
0"
07
#75
1"
17
b110 C
b10000000 B
#80
0"
07
#85
1"
17
b111 C
18
0L
b1 M
b0 O
0K
1L
b10 M
1K
b11 O
b0 B
0:
0^
0'
#90
0"
07
#95
1"
17
b0 C
08
0L
b1 M
b0 O
0K
1L
b10 M
1K
b10 O
b11 N
0L
b1 M
b0 O
0K
1L
b11 M
b100 O
09
1=
1^
1'
#100
0"
07
#105
1"
17
b100 N
0L
b1 M
b0 O
1L
0<
#110
0"
07
#115
1"
17
b0 N
0L
0(
#120
0"
07
#124
b11010010 #
1$
00
1.
0-
13
b1 O
#125
1"
17
b11010010 B
b1 N
b11010010 U
1:
b0 O
1L
b0 M
b10 O
1(
0=
0^
0'
#130
0"
07
#134
0$
03
0L
b1 M
b0 O
1L
b0 M
b10 O
#135
1"
17
b10 N
0T
0;
0L
b1 M
b0 O
1L
b10 M
1K
b10 O
19
1<
1^
1'
#140
0"
07
#145
1"
17
b1 C
b10100100 B
#150
0"
07
#155
1"
17
b10 C
b1001000 B
0:
0^
0'
#160
0"
07
#165
1"
17
b11 C
b10010000 B
1:
1^
1'
#170
0"
07
#175
1"
17
b100 C
b100000 B
0:
0^
0'
#180
0"
07
#185
1"
17
b101 C
b1000000 B
#190
0"
07
#195
1"
17
b110 C
b10000000 B
1:
1^
1'
#200
0"
07
#205
1"
17
b111 C
18
0L
b1 M
b0 O
0K
1L
b10 M
1K
b11 O
b0 B
0:
0^
0'
#210
0"
07
#215
1"
17
b0 C
08
0L
b1 M
b0 O
0K
1L
b10 M
1K
b10 O
b11 N
0L
b1 M
b0 O
0K
1L
b11 M
b100 O
09
1=
#220
0"
07
#225
1"
17
b100 N
0L
b1 M
b0 O
1L
0<
1^
1'
#230
0"
07
#235
1"
17
b0 N
0L
0(
