UART_RX/Deserializer.v
/******************************************************************************
*
* Module: Private - Deserializer Block 
*
* File Name: Deserializer.v
*
* Description:  This Block Is Used To Deserialize the data to out the parllel data
*              
*               
* Author: Mohamed A. Eladawy
*
*******************************************************************************/

//********************Port Declaration*************************//
module  Deserializer # (

parameter Number_Edges   = 4 , 
parameter DATA_WIDTH     = 8 ) //Paramters Block
  
(

input wire                        Deser_EN            ,  //Declaring the Variable As an Input Port with width 1 bit
input wire                        CLK                 ,  //Declaring the Variable As an Input Port with width 1 bit
input wire                        RST                 ,  //Declaring the Variable As an Input Port with width 1 bit
input wire                        Sampled_Bit_Deser   ,  //Declaring the Variable As an input Port with width 1 bit
input wire [Number_Edges-1 :0]    Edge_count          ,  //Declaring the Variable As an input Port with width 3 bit
output reg [DATA_WIDTH-1   :0]    P_Data_Deser           //Declaring the Variable As an output Port with width 1 bit 

); 
//****************** Parameeters Initialization  ****************//

localparam          ONE            = 1'b1   ,//initialize a parameter variable with a binary value 1
                    ZERO           = 1'b0   ;//initialize a parameter variable with a binary value 0
                    

//********************Internal Signal Declaration*****************//

reg [7:0]     P_Data_Deser_Comb ;  


//*************************** The RTL Code *****************************//
/*************** Starting The Sequential Always Block ***************/

always @(posedge CLK or negedge RST )

begin 
        if(!RST)
        
           begin
              
               P_Data_Deser <= 'b0 ;
                     
           end
  
      else if ( Deser_EN  && Edge_count == 3'b111  ) // && Edge_count == 3'b111 
        
           begin
            
            P_Data_Deser <=  {Sampled_Bit_Deser,P_Data_Deser[7:1]};
         
          end	
     else
      
      begin
        
         P_Data_Deser <= P_Data_Deser ;
      
      end 
end 


endmodule

UART_RX/Deserializer_tb.v
/******************************************************************************
*
* Module: Private - UART Transmiter Block
*
* File Name: UART_TX_tb.v
*
* Description:  this file is used for testing implementation of the UART Transmiter
*
* Author: Mohamed A. Eladawy
*
*******************************************************************************/
module  Deserializer_tb  () ;
  

// all design inputs are defined in testbench as reg to be used inside initial block 
// all design outputs are defined in testbench as wire   
reg                        Deser_EN_tb            ;  //Declaring the Variable As an Input Port with width 1 bit
reg                        CLK_tb                 ;  //Declaring the Variable As an Input Port with width 1 bit
reg                        RST_tb                 ;  //Declaring the Variable As an Input Port with width 1 bit
reg                        Sampled_Bit_Deser_tb   ;  //Declaring the Variable As an input Port with width 1 bit
reg  [2 :0]    Edge_count_tb         ;  //Declaring the Variable As an input Port with width 3 bit
wire [7 :0]   P_Data_Deser_tb        ;  //Declaring the Variable As an output Port with width 1 bit 

/***********************************************************************/ 
initial 
  begin
    $dumpfile(" Deserializer.vcd") ;
    $dumpvars ;
    //initial values
    RST_tb     = 1'b0     ;
    CLK_tb     = 1'b0     ;
    Sampled_Bit_Deser_tb = 1'b0 ;

   
/***********************************************************************/    
   
    $display ("TEST CASE 1") ;  // 
    #2
    RST_tb      = 1'b0  ;
    Deser_EN_tb = 1'b0  ; 
    #2
    RST_tb               = 1'b1         ;
    Deser_EN_tb          = 1'b1         ; 
    Sampled_Bit_Deser_tb = 1'b0         ;// at 4 0
    Edge_count_tb = 3'b111 ; 
    #6                              
    Sampled_Bit_Deser_tb = 1'b0         ; // at 10 0
    #10  
    Sampled_Bit_Deser_tb = 1'b1         ;  //at 20 1
    #10
    Sampled_Bit_Deser_tb = 1'b1         ;  //at 30  1 
    #10
    Sampled_Bit_Deser_tb = 1'b1         ; //at 40 1 
    #10
    Sampled_Bit_Deser_tb = 1'b0         ; //at 50 0 
    #10
    Sampled_Bit_Deser_tb = 1'b1         ; // at 60 1 
    #10
    Sampled_Bit_Deser_tb = 1'b1         ; // at 70 1 
    #10
    Deser_EN_tb          = 1'b0         ; 
/***********************************************************************/    
       

    #100
    $finish ;  
  
      
end 

// Clock Generator  
  always #5 CLK_tb = !CLK_tb ;
  
// instaniate design instance 
 Deserializer DUT (

.Deser_EN(Deser_EN_tb)                      ,
.CLK(CLK_tb)                      ,
.RST(RST_tb)           ,
.Sampled_Bit_Deser(Sampled_Bit_Deser_tb)   ,
.Edge_count(Edge_count_tb)           ,
.P_Data_Deser(P_Data_Deser_tb)      

);

  
endmodule

UART_RX/ Deserializer.vcd
$date
	Thu Oct 06 01:15:05 2022
$end
$version
	ModelSim Version 10.1d
$end
$timescale
	1ps
$end
$scope module Deserializer_tb $end
$var reg 1 ! Deser_EN_tb $end
$var reg 1 " CLK_tb $end
$var reg 1 # RST_tb $end
$var reg 1 $ Sampled_Bit_Deser_tb $end
$var reg 3 % Edge_count_tb [2:0] $end
$var wire 1 & P_Data_Deser_tb [7] $end
$var wire 1 ' P_Data_Deser_tb [6] $end
$var wire 1 ( P_Data_Deser_tb [5] $end
$var wire 1 ) P_Data_Deser_tb [4] $end
$var wire 1 * P_Data_Deser_tb [3] $end
$var wire 1 + P_Data_Deser_tb [2] $end
$var wire 1 , P_Data_Deser_tb [1] $end
$var wire 1 - P_Data_Deser_tb [0] $end
$scope module DUT $end
$var parameter 32 . Number_Edges $end
$var parameter 32 / DATA_WIDTH $end
$var parameter 1 0 ONE $end
$var parameter 1 1 ZERO $end
$var wire 1 2 Deser_EN $end
$var wire 1 3 CLK $end
$var wire 1 4 RST $end
$var wire 1 5 Sampled_Bit_Deser $end
$var wire 1 6 Edge_count [2] $end
$var wire 1 7 Edge_count [1] $end
$var wire 1 8 Edge_count [0] $end
$var reg 8 9 P_Data_Deser [7:0] $end
$var reg 8 : P_Data_Deser_Comb [7:0] $end
$upscope $end
$upscope $end
$enddefinitions $end
#0
$dumpvars
x!
0"
0#
0$
bx %
b0 9
bx :
b11 .
b1000 /
b1 0
b0 1
0-
0,
0+
0*
0)
0(
0'
0&
x8
x7
x6
05
04
03
x2
$end
#2
0!
02
#4
1#
1!
b111 %
12
18
17
16
14
#5
1"
13
#10
0"
03
#15
1"
13
#20
1$
0"
15
03
#25
1"
13
b1 9
1-
b10 9
0-
1,
#30
0"
03
#35
1"
13
b11 9
1-
b110 9
0-
1+
#40
0"
03
#45
1"
13
b111 9
1-
b1110 9
0-
1*
#50
0$
0"
05
03
#55
1"
13
b11100 9
0,
1)
#60
1$
0"
15
03
#65
1"
13
b11101 9
1-
b111010 9
0-
1,
0+
1(
#70
0"
03
#75
1"
13
b111011 9
1-
b1110110 9
0-
1+
0*
1'
#80
0!
0"
02
03
